Workbook

Sheet Informe BBVA
A1: F.Valor | B1: Fecha | C1: Periodo | D1: Concepto | E1: Movimiento | F1: Importe | G1: Divisa | H1: Disponible | I1: Divisa2 | J1: Observaciones | K1: Subcatergoria | L1: Categoria
A2: 31/10/2025 | B2: 31/10/2025 | C2: =MONTH(A2) -> 10 | D2: Acciona motosharing | E2: Pago con tarjeta | F2: -4.88 | G2: EUR | H2: 5664.75 | I2: EUR | J2: 4940197133530195 ACCIONA MOTOSHARING ALCOBENDAS ES | K2: Transporte | L2: =VLOOKUP(K2,'COD.'!$A$1:$B$39,2,0) -> Otros Gastos Generales
A3: 30/10/2025 | B3: 31/10/2025 | C3: =MONTH(A3) -> 10 | D3: Netflix.com | E3: Pago con tarjeta | F3: -6.99 | G3: EUR | H3: 5669.63 | I3: EUR | J3: 4940197133530195 Netflix.com | K3: Netfix | L3: =VLOOKUP(K3,'COD.'!$A$1:$B$39,2,0) -> Ocio y Entretenimiento
A4: 31/10/2025 | B4: 31/10/2025 | C4: =MONTH(A4) -> 10 | D4: Adeudo de endesa | E4: Adeudo nº 2025303002749399 | F4: -67.81 | G4: EUR | H4: 5676.62 | I4: EUR | J4: N 2025303002749399 ENERGIA XXI CPVR | K4: Luz | L4: =VLOOKUP(K4,'COD.'!$A$1:$B$39,2,0) -> Suministros
A5: 31/10/2025 | B5: 31/10/2025 | C5: =MONTH(A5) -> 10 | D5: Cargo por amortizacion de prestamo/credito | F5: -461.91 | G5: EUR | H5: 5744.43 | I5: EUR | J5: 0182-3247-22-0830147409 | K5: Hipoteca | L5: =VLOOKUP(K5,'COD.'!$A$1:$B$39,2,0) -> Vivienda y Préstamos
A6: 30/10/2025 | B6: 30/10/2025 | C6: =MONTH(A6) -> 10 | D6: Frankingfurt | E6: Pago con tarjeta | F6: -21.6 | G6: EUR | H6: 6206.34 | I6: EUR | J6: 4940197133530195 FRANKINGFURT SANTA COLOMA ES | K6: Bar/Restaurante | L6: =VLOOKUP(K6,'COD.'!$A$1:$B$39,2,0) -> Ocio y Entretenimiento
A7: 30/10/2025 | B7: 30/10/2025 | C7: =MONTH(A7) -> 10 | D7: Bar cafeteria | E7: Pago con tarjeta | F7: -3.9 | G7: EUR | H7: 6227.94 | I7: EUR | J7: 4940197133530195 BAR CAFETERIA SANTA COLOMA ES | K7: Bar/Restaurante | L7: =VLOOKUP(K7,'COD.'!$A$1:$B$39,2,0) -> Ocio y Entretenimiento
A8: 30/10/2025 | B8: 30/10/2025 | C8: =MONTH(A8) -> 10 | D8: Adeudo de aguas de barcelona | E8: Adeudo nº 2025303002474367 | F8: -44.47 | G8: EUR | H8: 6231.84 | I8: EUR | J8: N 2025303002474367 AIGUES DE BARCELONA | K8: Agua | L8: =VLOOKUP(K8,'COD.'!$A$1:$B$39,2,0) -> Suministros
A9: 30/10/2025 | B9: 30/10/2025 | C9: =MONTH(A9) -> 10 | D9: Abono de nómina | E9: Transferencia nomina | F9: 1867.53 | G9: EUR | H9: 6276.31 | I9: EUR | J9: Transferencia nomina | K9: Nomina | L9: =VLOOKUP(K9,'COD.'!$A$1:$B$39,2,0) -> Transferencias y Efectivo
A10: 28/10/2025 | B10: 28/10/2025 | C10: =MONTH(A10) -> 10 | D10: Social working dogs sccl | E10: Pago con tarjeta | F10: -29.95 | G10: EUR | H10: 4408.78 | I10: EUR | J10: 4940197133530195 SOCIAL WORKING DOGS SCCL LLIA D'AMUNTES | K10: Mascotas | L10: =VLOOKUP(K10,'COD.'!$A$1:$B$39,2,0) -> Supermercado
A11: 23/10/2025 | B11: 27/10/2025 | C11: =MONTH(A11) -> 10 | D11: Paypal *spotify*p3bbd12eb | E11: Pago con tarjeta | F11: -11.99 | G11: EUR | H11: 4438.73 | I11: EUR | J11: 4940197133530195 PAYPAL *SPOTIFY*P3BBD12EB | K11: Spotify | L11: =VLOOKUP(K11,'COD.'!$A$1:$B$39,2,0) -> Ocio y Entretenimiento
A12: 26/10/2025 | B12: 27/10/2025 | C12: =MONTH(A12) -> 10 | D12: Farmacia jordi bomcompte | E12: Pago con tarjeta | F12: -3.26 | G12: EUR | H12: 4450.72 | I12: EUR | J12: 4940197133530195 FARMACIA JORDI BOMCOMPTE PLA, PASSATGEES | K12: Farmacia | L12: =VLOOKUP(K12,'COD.'!$A$1:$B$39,2,0) -> Salud y Cuidado
A13: 25/10/2025 | B13: 27/10/2025 | C13: =MONTH(A13) -> 10 | D13: Kiwoko fabra | E13: Pago con tarjeta | F13: -17.89 | G13: EUR | H13: 4453.98 | I13: EUR | J13: 4940197133530195 KIWOKO FABRA BARCELONA ES | K13: Mascotas | L13: =VLOOKUP(K13,'COD.'!$A$1:$B$39,2,0) -> Supermercado
A14: 25/10/2025 | B14: 27/10/2025 | C14: =MONTH(A14) -> 10 | D14: Bar-rest. bell more | E14: Pago con tarjeta | F14: -2.9 | G14: EUR | H14: 4471.87 | I14: EUR | J14: 4940197133530195 Bar-Rest. Bell More BARCELONA ES | K14: Bar/Restaurante | L14: =VLOOKUP(K14,'COD.'!$A$1:$B$39,2,0) -> Ocio y Entretenimiento
A15: 24/10/2025 | B15: 27/10/2025 | C15: =MONTH(A15) -> 10 | D15: Bar lido | E15: Pago con tarjeta | F15: -7.95 | G15: EUR | H15: 4474.77 | I15: EUR | J15: 4940197133530195 BAR LIDO BARCELONA ES | K15: Bar/Restaurante | L15: =VLOOKUP(K15,'COD.'!$A$1:$B$39,2,0) -> Ocio y Entretenimiento
A16: 24/10/2025 | B16: 24/10/2025 | C16: =MONTH(A16) -> 10 | D16: Hyde park | E16: Pago con tarjeta | F16: -1.7 | G16: EUR | H16: 4482.72 | I16: EUR | J16: 4940197133530195 HYDE PARK BARCELONA ES | K16: Bar/Restaurante | L16: =VLOOKUP(K16,'COD.'!$A$1:$B$39,2,0) -> Ocio y Entretenimiento
A17: 24/10/2025 | B17: 24/10/2025 | C17: =MONTH(A17) -> 10 | D17: L estanc de la merce | E17: Pago con tarjeta | F17: -6.3 | G17: EUR | H17: 4484.42 | I17: EUR | J17: 4940197133530195 L ESTANC DE LA MERCE BARCELONA ES | K17: Tabaco | L17: =VLOOKUP(K17,'COD.'!$A$1:$B$39,2,0) -> Otros Gastos Generales
... A86: 30/09/2025 | B86: 30/09/2025 | C86: =MONTH(A86) -> 9 | D86: Druni sta coloma gramenet | E86: Pago con tarjeta | F86: -26.95 | G86: EUR | H86: 6060.2 | I86: EUR | J86: 4940197133530195 DRUNI STA COLOMA GRAMENETSANTA COLOMA ES | K86: Compras | L86: =VLOOKUP(K86,'COD.'!$A$1:$B$39,2,0) -> Ocio y Entretenimiento
A87: 30/09/2025 | B87: 30/09/2025 | C87: =MONTH(A87) -> 9 | D87: Cargo por amortizacion de prestamo/credito | F87: -461.91 | G87: EUR | H87: 6087.15 | I87: EUR | J87: 0182-3247-22-0830147409 | K87: Hipoteca | L87: =VLOOKUP(K87,'COD.'!$A$1:$B$39,2,0) -> Vivienda y Préstamos
A88: 29/09/2025 | B88: 29/09/2025 | C88: =MONTH(A88) -> 9 | D88: Kiwoko fabra | E88: Pago con tarjeta | F88: -38.65 | G88: EUR | H88: 6549.06 | I88: EUR | J88: 4940197133530195 KIWOKO FABRA BARCELONA ES | K88: Mascotas | L88: =VLOOKUP(K88,'COD.'!$A$1:$B$39,2,0) -> Supermercado
A89: 28/09/2025 | B89: 29/09/2025 | C89: =MONTH(A89) -> 9 | D89: Condis supermercat | E89: Pago con tarjeta | F89: -5.23 | G89: EUR | H89: 6587.71 | I89: EUR | J89: 4940197133530195 CONDIS SUPERMERCAT STA. COLOMA DES | K89: Supermercado | L89: =VLOOKUP(K89,'COD.'!$A$1:$B$39,2,0) -> Supermercado
A90: 26/09/2025 | B90: 26/09/2025 | C90: =MONTH(A90) -> 9 | D90: La santa | E90: Pago con tarjeta | F90: -4.1 | G90: EUR | H90: 6592.94 | I90: EUR | J90: 4940197133530195 LA SANTA ESPLUGUES DE ES | K90: Bar/Restaurante | L90: =VLOOKUP(K90,'COD.'!$A$1:$B$39,2,0) -> Ocio y Entretenimiento
A91: 26/09/2025 | B91: 26/09/2025 | C91: =MONTH(A91) -> 9 | D91: Terranova 55 | E91: Pago con tarjeta | F91: -36.95 | G91: EUR | H91: 6597.04 | I91: EUR | J91: 4940197133530195 TERRANOVA 55 SANTA COLOMA ES | K91: Mascotas | L91: =VLOOKUP(K91,'COD.'!$A$1:$B$39,2,0) -> Supermercado
A92: 26/09/2025 | B92: 26/09/2025 | C92: =MONTH(A92) -> 9 | D92: Forn padro | E92: Pago con tarjeta | F92: -1.55 | G92: EUR | H92: 6633.99 | I92: EUR | J92: 4940197133530195 FORN PADRO SANTA COLOMA ES | K92: Bar/Restaurante | L92: =VLOOKUP(K92,'COD.'!$A$1:$B$39,2,0) -> Ocio y Entretenimiento
A93: 26/09/2025 | B93: 26/09/2025 | C93: =MONTH(A93) -> 9 | D93: Abono de nómina | E93: Transferencia nomina | F93: 1867.53 | G93: EUR | H93: 6635.54 | I93: EUR | J93: Transferencia nomina | K93: Nomina | L93: =VLOOKUP(K93,'COD.'!$A$1:$B$39,2,0) -> Transferencias y Efectivo
A94: 26/09/2025 | B94: 26/09/2025 | C94: =MONTH(A94) -> 9 | D94: Condis supermercat | E94: Pago con tarjeta | F94: -1.02 | G94: EUR | H94: 4768.01 | I94: EUR | J94: 4940197133530195 CONDIS SUPERMERCAT STA. COLOMA DES | K94: Supermercado | L94: =VLOOKUP(K94,'COD.'!$A$1:$B$39,2,0) -> Supermercado
A95: 26/09/2025 | B95: 26/09/2025 | C95: =MONTH(A95) -> 9 | D95: Rostisseria la katia | E95: Pago con tarjeta | F95: -22.75 | G95: EUR | H95: 4769.03 | I95: EUR | J95: 4940197133530195 ROSTISSERIA LA KATIA STA. COLOMA DES | K95: Bar/Restaurante | L95: =VLOOKUP(K95,'COD.'!$A$1:$B$39,2,0) -> Ocio y Entretenimiento
A96: 26/09/2025 | B96: 26/09/2025 | C96: =MONTH(A96) -> 9 | D96: Farmacia jordi bomcompte | E96: Pago con tarjeta | F96: -3.26 | G96: EUR | H96: 4791.78 | I96: EUR | J96: 4940197133530195 FARMACIA JORDI BOMCOMPTE SANTA COLOMA ES | K96: Farmacia | L96: =VLOOKUP(K96,'COD.'!$A$1:$B$39,2,0) -> Salud y Cuidado
A97: 25/09/2025 | B97: 26/09/2025 | C97: =MONTH(A97) -> 9 | D97: Frankingfurt | E97: Pago con tarjeta | F97: -15.7 | G97: EUR | H97: 4795.04 | I97: EUR | J97: 4940197133530195 FRANKINGFURT SANTA COLOMA ES | K97: Bar/Restaurante | L97: =VLOOKUP(K97,'COD.'!$A$1:$B$39,2,0) -> Ocio y Entretenimiento
A98: 25/09/2025 | B98: 25/09/2025 | C98: =MONTH(A98) -> 9 | D98: La botiga mes que gossos | E98: Pago con tarjeta | F98: -27.8 | G98: EUR | H98: 4810.74 | I98: EUR | J98: 4940197133530195 LA BOTIGA MES QUE GOSSOS SANTA COLOMA ES | K98: Mascotas | L98: =VLOOKUP(K98,'COD.'!$A$1:$B$39,2,0) -> Supermercado
A99: 25/09/2025 | B99: 25/09/2025 | C99: =MONTH(A99) -> 9 | D99: Cerveceria thor | E99: Pago con tarjeta | F99: -1.7 | G99: EUR | H99: 4838.54 | I99: EUR | J99: 4940197133530195 cerveceria thor PLA, PASSATGEES | K99: Bar/Restaurante | L99: =VLOOKUP(K99,'COD.'!$A$1:$B$39,2,0) -> Ocio y Entretenimiento
... A177: 31/08/2025 | B177: 01/09/2025 | C177: =MONTH(A177) -> 8 | D177: Cerveceria thor | E177: Pago con tarjeta | F177: -1.2 | G177: EUR | H177: 6401.64 | I177: EUR | J177: 4940197133530195 cerveceria thor PLA, PASSATGEES | K177: Bar/Restaurante | L177: =VLOOKUP(K177,'COD.'!$A$1:$B$39,2,0) -> Ocio y Entretenimiento
A178: 31/08/2025 | B178: 01/09/2025 | C178: =MONTH(A178) -> 8 | D178: Cargo por amortizacion de prestamo/credito | F178: -461.91 | G178: EUR | H178: 6402.84 | I178: EUR | J178: 0182-3247-22-0830147409 | K178: Hipoteca | L178: =VLOOKUP(K178,'COD.'!$A$1:$B$39,2,0) -> Vivienda y Préstamos
A179: 30/08/2025 | B179: 01/09/2025 | C179: =MONTH(A179) -> 8 | D179: La rotonda masnou | E179: Pago con tarjeta | F179: -9 | G179: EUR | H179: 6864.75 | I179: EUR | J179: 4940197133530195 LA ROTONDA MASNOU EL MASNOU ES | K179: Bar/Restaurante | L179: =VLOOKUP(K179,'COD.'!$A$1:$B$39,2,0) -> Ocio y Entretenimiento
A180: 30/08/2025 | B180: 01/09/2025 | C180: =MONTH(A180) -> 8 | D180: Macxipa avda. generalitat | E180: Pago con tarjeta | F180: -2.26 | G180: EUR | H180: 6873.75 | I180: EUR | J180: 4940197133530195 MACXIPA AVDA. GENERALITATSTA. COLOMA ES | K180: Bar/Restaurante | L180: =VLOOKUP(K180,'COD.'!$A$1:$B$39,2,0) -> Ocio y Entretenimiento
A181: 29/08/2025 | B181: 29/08/2025 | C181: =MONTH(A181) -> 8 | D181: Druni sta coloma gramenet | E181: Pago con tarjeta | F181: -1.99 | G181: EUR | H181: 6876.01 | I181: EUR | J181: 4940197133530195 DRUNI STA COLOMA GRAMENETSANTA COLOMA ES | K181: compras | L181: =VLOOKUP(K181,'COD.'!$A$1:$B$39,2,0) -> Ocio y Entretenimiento
A182: 29/08/2025 | B182: 29/08/2025 | C182: =MONTH(A182) -> 8 | D182: Abono por fraccionamiento de gastos | E182: Abono capital préstamo | F182: 699.84 | G182: EUR | H182: 6878 | I182: EUR | J182: 8123450000175812 01827013 704 | K182: Cuota mensual de fraccionamiento de gastos | L182: =VLOOKUP(K182,'COD.'!$A$1:$B$39,2,0) -> Vivienda y Préstamos
A183: 28/08/2025 | B183: 29/08/2025 | C183: =MONTH(A183) -> 8 | D183: 0453-consum b. fabra y pu | E183: Pago con tarjeta | F183: -11.5 | G183: EUR | H183: 6178.16 | I183: EUR | J183: 4940197133530195 0453-CONSUM B. FABRA Y PUBARCELONA ES | K183: Supermercado | L183: =VLOOKUP(K183,'COD.'!$A$1:$B$39,2,0) -> Supermercado
A184: 28/08/2025 | B184: 29/08/2025 | C184: =MONTH(A184) -> 8 | D184: Cal pesca | E184: Pago con tarjeta | F184: -26.2 | G184: EUR | H184: 6189.66 | I184: EUR | J184: 4940197133530195 CAL PESCA BARCELONA ES | K184: Bar/Restaurante | L184: =VLOOKUP(K184,'COD.'!$A$1:$B$39,2,0) -> Ocio y Entretenimiento
A185: 28/08/2025 | B185: 28/08/2025 | C185: =MONTH(A185) -> 8 | D185: Estanco expendiduria 134 | E185: Pago con tarjeta | F185: -1.5 | G185: EUR | H185: 6215.86 | I185: EUR | J185: 4940197133530195 ESTANCO EXPENDIDURIA 134 BARCELONA ES | K185: Tabaco | L185: =VLOOKUP(K185,'COD.'!$A$1:$B$39,2,0) -> Otros Gastos Generales
A186: 28/08/2025 | B186: 28/08/2025 | C186: =MONTH(A186) -> 8 | D186: Adeudo de aguas de barcelona | E186: Adeudo nº 2025240002014457 | F186: -44.47 | G186: EUR | H186: 6217.36 | I186: EUR | J186: N 2025240002014457 AIGUES DE BARCELONA | K186: Agua | L186: =VLOOKUP(K186,'COD.'!$A$1:$B$39,2,0) -> Suministros
A187: 27/08/2025 | B187: 27/08/2025 | C187: =MONTH(A187) -> 8 | D187: Expendiduria n.2 | E187: Pago con tarjeta | F187: -7.5 | G187: EUR | H187: 6261.83 | I187: EUR | J187: 4940197133530195 EXPENDIDURIA N.2 SANTA COLOMA ES | K187: Tabaco | L187: =VLOOKUP(K187,'COD.'!$A$1:$B$39,2,0) -> Otros Gastos Generales
A188: 27/08/2025 | B188: 27/08/2025 | C188: =MONTH(A188) -> 8 | D188: Farmacia reixach - de pab | E188: Pago con tarjeta | F188: -47.61 | G188: EUR | H188: 6269.33 | I188: EUR | J188: 4940197133530195 FARMACIA REIXACH - DE PABBARCELONA ES | K188: Farmacia | L188: =VLOOKUP(K188,'COD.'!$A$1:$B$39,2,0) -> Salud y Cuidado
A189: 25/08/2025 | B189: 27/08/2025 | C189: =MONTH(A189) -> 8 | D189: Amzn mktp es*r46rb6a34 | E189: Pago con tarjeta | F189: -44.75 | G189: EUR | H189: 6316.94 | I189: EUR | J189: 4940197133530195 AMZN Mktp ES*R46RB6A34 | K189: Compras | L189: =VLOOKUP(K189,'COD.'!$A$1:$B$39,2,0) -> Ocio y Entretenimiento
A190: 23/08/2025 | B190: 27/08/2025 | C190: =MONTH(A190) -> 8 | D190: Paypal *spotify*p39cf6729 | E190: Pago con tarjeta | F190: -10.99 | G190: EUR | H190: 6361.69 | I190: EUR | J190: 4940197133530195 PAYPAL *SPOTIFY*P39CF6729 | K190: Spotify | L190: =VLOOKUP(K190,'COD.'!$A$1:$B$39,2,0) -> Ocio y Entretenimiento
... A268: 29/07/2025 | B268: 31/07/2025 | C268: =MONTH(A268) -> 7 | D268: Onlinetravelpr united | E268: Pago con tarjeta | F268: 73.58 | G268: EUR | H268: 6027.36 | I268: EUR | J268: 4940197133530195 onlinetravelpr UNITED | K268: Viajes | L268: =VLOOKUP(K268,'COD.'!$A$1:$B$39,2,0) -> Ocio y Entretenimiento
A269: 31/07/2025 | B269: 31/07/2025 | C269: =MONTH(A269) -> 7 | D269: Cargo por amortizacion de prestamo/credito | F269: -461.91 | G269: EUR | H269: 5953.78 | I269: EUR | J269: 0182-3247-22-0830147409 | K269: Hipoteca | L269: =VLOOKUP(K269,'COD.'!$A$1:$B$39,2,0) -> Vivienda y Préstamos
A270: 30/07/2025 | B270: 30/07/2025 | C270: =MONTH(A270) -> 7 | D270: Bar noray | E270: Pago con tarjeta | F270: -5.6 | G270: EUR | H270: 6415.69 | I270: EUR | J270: 4940197133530195 BAR NORAY BARCELONA ES | K270: Bar/Restaurante | L270: =VLOOKUP(K270,'COD.'!$A$1:$B$39,2,0) -> Ocio y Entretenimiento
A271: 30/07/2025 | B271: 30/07/2025 | C271: =MONTH(A271) -> 7 | D271: Bizum | E271: Enviado: brunch | F271: -75 | G271: EUR | H271: 6421.29 | I271: EUR | J271: ENVIADO: Brunch | K271: Bizum | L271: =VLOOKUP(K271,'COD.'!$A$1:$B$39,2,0) -> Transferencias y Efectivo
A272: 29/07/2025 | B272: 29/07/2025 | C272: =MONTH(A272) -> 7 | D272: Consum b.gr.s.andreu | E272: Pago con tarjeta | F272: -21.03 | G272: EUR | H272: 6496.29 | I272: EUR | J272: 4940197133530195 CONSUM B.GR.S.ANDREU BARCELONA ES | K272: Supermercado | L272: =VLOOKUP(K272,'COD.'!$A$1:$B$39,2,0) -> Supermercado
A273: 29/07/2025 | B273: 29/07/2025 | C273: =MONTH(A273) -> 7 | D273: Casa arana | E273: Pago con tarjeta | F273: -13.8 | G273: EUR | H273: 6517.32 | I273: EUR | J273: 4940197133530195 CASA ARANA BARCELONA ES | K273: Bar/Restaurante | L273: =VLOOKUP(K273,'COD.'!$A$1:$B$39,2,0) -> Ocio y Entretenimiento
A274: 28/07/2025 | B274: 28/07/2025 | C274: =MONTH(A274) -> 7 | D274: Juana dog sant andreu pc1 | E274: Pago con tarjeta | F274: -62.55 | G274: EUR | H274: 6531.12 | I274: EUR | J274: 4940197133530195 JUANA DOG SANT ANDREU PC1BARCELONA ES | K274: Mascotas | L274: =VLOOKUP(K274,'COD.'!$A$1:$B$39,2,0) -> Supermercado
A275: 28/07/2025 | B275: 28/07/2025 | C275: =MONTH(A275) -> 7 | D275: Air house park barcelona | E275: Pago con tarjeta | F275: -1.7 | G275: EUR | H275: 6593.67 | I275: EUR | J275: 4940197133530195 AIR HOUSE PARK BARCELONA BADALONA ES | K275: Bar/Restaurante | L275: =VLOOKUP(K275,'COD.'!$A$1:$B$39,2,0) -> Ocio y Entretenimiento
A276: 28/07/2025 | B276: 28/07/2025 | C276: =MONTH(A276) -> 7 | D276: Adeudo de endesa | E276: Adeudo nº 2025209001644442 | F276: -89.77 | G276: EUR | H276: 6595.37 | I276: EUR | J276: N 2025209001644442 ENERGIA XXI CPVR | K276: Luz | L276: =VLOOKUP(K276,'COD.'!$A$1:$B$39,2,0) -> Suministros
A277: 28/07/2025 | B277: 28/07/2025 | C277: =MONTH(A277) -> 7 | D277: Abono de nómina | E277: Transferencia nomina | F277: 1867.53 | G277: EUR | H277: 6685.14 | I277: EUR | J277: Transferencia nomina | K277: Nomina | L277: =VLOOKUP(K277,'COD.'!$A$1:$B$39,2,0) -> Transferencias y Efectivo
A278: 27/07/2025 | B278: 28/07/2025 | C278: =MONTH(A278) -> 7 | D278: J.c. celler vermuteria | E278: Pago con tarjeta | F278: -4.05 | G278: EUR | H278: 4817.61 | I278: EUR | J278: 4940197133530195 J.C. CELLER VERMUTERIA SANTA COLOMA ES | K278: Bar/Restaurante | L278: =VLOOKUP(K278,'COD.'!$A$1:$B$39,2,0) -> Ocio y Entretenimiento
A279: 27/07/2025 | B279: 28/07/2025 | C279: =MONTH(A279) -> 7 | D279: Macxipa avda. generalitat | E279: Pago con tarjeta | F279: -3.59 | G279: EUR | H279: 4821.66 | I279: EUR | J279: 4940197133530195 MACXIPA AVDA. GENERALITATSTA. COLOMA ES | K279: Bar/Restaurante | L279: =VLOOKUP(K279,'COD.'!$A$1:$B$39,2,0) -> Ocio y Entretenimiento
A280: 26/07/2025 | B280: 28/07/2025 | C280: =MONTH(A280) -> 7 | D280: Micande | E280: Pago con tarjeta | F280: -35 | G280: EUR | H280: 4825.25 | I280: EUR | J280: 4940197133530195 MICANDE BADALONA ES | K280: Bar/Restaurante | L280: =VLOOKUP(K280,'COD.'!$A$1:$B$39,2,0) -> Ocio y Entretenimiento
A281: 26/07/2025 | B281: 28/07/2025 | C281: =MONTH(A281) -> 7 | D281: Micande | E281: Pago con tarjeta | F281: -6.7 | G281: EUR | H281: 4860.25 | I281: EUR | J281: 4940197133530195 MICANDE BADALONA ES | K281: Bar/Restaurante | L281: =VLOOKUP(K281,'COD.'!$A$1:$B$39,2,0) -> Ocio y Entretenimiento
... A349: 30/06/2025 | B349: 30/06/2025 | C349: =MONTH(A349) -> 6 | D349: Adeudo de endesa | E349: Adeudo nº 2025178003440953 | F349: -52.62 | G349: EUR | H349: 6422.54 | I349: EUR | J349: N 2025178003440953 ENERGIA XXI CPVR | K349: Luz | L349: =VLOOKUP(K349,'COD.'!$A$1:$B$39,2,0) -> Suministros
A350: 30/06/2025 | B350: 30/06/2025 | C350: =MONTH(A350) -> 6 | D350: Cargo por amortizacion de prestamo/credito | F350: -431.42 | G350: EUR | H350: 6475.16 | I350: EUR | J350: 0182-3247-22-0830147409 | K350: Hipoteca | L350: =VLOOKUP(K350,'COD.'!$A$1:$B$39,2,0) -> Vivienda y Préstamos
A351: 29/06/2025 | B351: 30/06/2025 | C351: =MONTH(A351) -> 6 | D351: Expendeduria n. 8 | E351: Pago con tarjeta | F351: -7.4 | G351: EUR | H351: 6906.58 | I351: EUR | J351: 4940197133530195 EXPENDEDURIA N. 8 STA COLOMA GRES | K351: Tabaco | L351: =VLOOKUP(K351,'COD.'!$A$1:$B$39,2,0) -> Otros Gastos Generales
A352: 28/06/2025 | B352: 30/06/2025 | C352: =MONTH(A352) -> 6 | D352: Ret. efectivo a debito con tarj. en cajero. aut. | E352: Otros | F352: -20 | G352: EUR | H352: 6913.98 | I352: EUR | J352: 4940197133530195 01820835 999 | K352: Limpieza casa | L352: =VLOOKUP(K352,'COD.'!$A$1:$B$39,2,0) -> Ocio y Entretenimiento
A353: 28/06/2025 | B353: 30/06/2025 | C353: =MONTH(A353) -> 6 | D353: Pastisseria glass | E353: Pago con tarjeta | F353: -32 | G353: EUR | H353: 6933.98 | I353: EUR | J353: 4940197133530195 PASTISSERIA GLASS SANTA COLOMA ES | K353: Bar/Restaurante | L353: =VLOOKUP(K353,'COD.'!$A$1:$B$39,2,0) -> Ocio y Entretenimiento
A354: 28/06/2025 | B354: 30/06/2025 | C354: =MONTH(A354) -> 6 | D354: Delicatessen argentina | E354: Pago con tarjeta | F354: -16.7 | G354: EUR | H354: 6965.98 | I354: EUR | J354: 4940197133530195 DELICATESSEN ARGENTINA BARCELONA ES | K354: Bar/Restaurante | L354: =VLOOKUP(K354,'COD.'!$A$1:$B$39,2,0) -> Ocio y Entretenimiento
A355: 27/06/2025 | B355: 27/06/2025 | C355: =MONTH(A355) -> 6 | D355: Suca'l sant andreu | E355: Pago con tarjeta | F355: -5.85 | G355: EUR | H355: 6982.68 | I355: EUR | J355: 4940197133530195 SUCA'L SANT ANDREU BARCELONA ES | K355: Bar/Restaurante | L355: =VLOOKUP(K355,'COD.'!$A$1:$B$39,2,0) -> Ocio y Entretenimiento
A356: 27/06/2025 | B356: 27/06/2025 | C356: =MONTH(A356) -> 6 | D356: Gasch xarcuters sl | E356: Pago con tarjeta | F356: -41.56 | G356: EUR | H356: 6988.53 | I356: EUR | J356: 4940197133530195 GASCH XARCUTERS SL BARCELONA ES | K356: Supermercado | L356: =VLOOKUP(K356,'COD.'!$A$1:$B$39,2,0) -> Supermercado
A357: 27/06/2025 | B357: 27/06/2025 | C357: =MONTH(A357) -> 6 | D357: Varios servicio c. loterias | E357: Otros | F357: -10 | G357: EUR | H357: 7030.09 | I357: EUR | J357: 4940197133530195 TULOTERO MADRID ES | K357: Loteria | L357: =VLOOKUP(K357,'COD.'!$A$1:$B$39,2,0) -> Ocio y Entretenimiento
A358: 24/06/2025 | B358: 27/06/2025 | C358: =MONTH(A358) -> 6 | D358: Amazon* yw5xq8z45 | E358: Pago con tarjeta | F358: -40.8 | G358: EUR | H358: 7040.09 | I358: EUR | J358: 4940197133530195 AMAZON* YW5XQ8Z45 | K358: Compras | L358: =VLOOKUP(K358,'COD.'!$A$1:$B$39,2,0) -> Ocio y Entretenimiento
A359: 27/06/2025 | B359: 27/06/2025 | C359: =MONTH(A359) -> 6 | D359: Abono de nómina | E359: Transferencia nomina | F359: 1867.53 | G359: EUR | H359: 7080.89 | I359: EUR | J359: Transferencia nomina | K359: Nomina | L359: =VLOOKUP(K359,'COD.'!$A$1:$B$39,2,0) -> Transferencias y Efectivo
A360: 27/06/2025 | B360: 27/06/2025 | C360: =MONTH(A360) -> 6 | D360: T mobilitat. app | E360: Pago con tarjeta | F360: -12.55 | G360: EUR | H360: 5213.36 | I360: EUR | J360: 4940197133530195 T MOBILITAT. APP HOSPITALET DEES | K360: Transporte | L360: =VLOOKUP(K360,'COD.'!$A$1:$B$39,2,0) -> Otros Gastos Generales
A361: 27/06/2025 | B361: 27/06/2025 | C361: =MONTH(A361) -> 6 | D361: El raco del cafe | E361: Pago con tarjeta | F361: -5.75 | G361: EUR | H361: 5225.91 | I361: EUR | J361: 4940197133530195 EL RACO DEL CAFE SANTA COLOMA ES | K361: Bar/Restaurante | L361: =VLOOKUP(K361,'COD.'!$A$1:$B$39,2,0) -> Ocio y Entretenimiento
A362: 26/06/2025 | B362: 26/06/2025 | C362: =MONTH(A362) -> 6 | D362: Swing | E362: Pago con tarjeta | F362: -22.99 | G362: EUR | H362: 5231.66 | I362: EUR | J362: 4940197133530195 SWING SANTA COLOMA ES | K362: Compras | L362: =VLOOKUP(K362,'COD.'!$A$1:$B$39,2,0) -> Ocio y Entretenimiento
... A440: 31/05/2025 | B440: 02/06/2025 | C440: =MONTH(A440) -> 5 | D440: Lady nail | E440: Pago con tarjeta | F440: -17 | G440: EUR | H440: 6559.62 | I440: EUR | J440: 4940197133530195 LADY NAIL BARCELONA ES | K440: Uñas | L440: =VLOOKUP(K440,'COD.'!$A$1:$B$39,2,0) -> Ocio y Entretenimiento
A441: 31/05/2025 | B441: 02/06/2025 | C441: =MONTH(A441) -> 5 | D441: Cargo por amortizacion de prestamo/credito | F441: -431.33 | G441: EUR | H441: 6576.62 | I441: EUR | J441: 0182-3247-22-0830147409 | K441: Hipoteca | L441: =VLOOKUP(K441,'COD.'!$A$1:$B$39,2,0) -> Vivienda y Préstamos
A442: 13/05/2025 | B442: 30/05/2025 | C442: =MONTH(A442) -> 5 | D442: Temu.com | E442: Pago con tarjeta | F442: 32.49 | G442: EUR | H442: 7007.95 | I442: EUR | J442: 4940197133530195 TEMU.COM | K442: Compras | L442: =VLOOKUP(K442,'COD.'!$A$1:$B$39,2,0) -> Ocio y Entretenimiento
A443: 30/05/2025 | B443: 30/05/2025 | C443: =MONTH(A443) -> 5 | D443: Rua taverna gastronomica | E443: Pago con tarjeta | F443: -14 | G443: EUR | H443: 6975.46 | I443: EUR | J443: 4940197133530195 RUA TAVERNA GASTRONOMICA BARCELONA ES | K443: Bar/Restaurante | L443: =VLOOKUP(K443,'COD.'!$A$1:$B$39,2,0) -> Ocio y Entretenimiento
A444: 29/05/2025 | B444: 29/05/2025 | C444: =MONTH(A444) -> 5 | D444: Cafeteria forn de pa dol | E444: Pago con tarjeta | F444: -1.6 | G444: EUR | H444: 6989.46 | I444: EUR | J444: 4940197133530195 CAFETERIA FORN DE PA DOL SANTA COLOMA ES | K444: Bar/Restaurante | L444: =VLOOKUP(K444,'COD.'!$A$1:$B$39,2,0) -> Ocio y Entretenimiento
A445: 29/05/2025 | B445: 29/05/2025 | C445: =MONTH(A445) -> 5 | D445: Bodega manelic | E445: Pago con tarjeta | F445: -3.6 | G445: EUR | H445: 6991.06 | I445: EUR | J445: 4940197133530195 BODEGA MANELIC SANTA COLOMA ES | K445: Bar/Restaurante | L445: =VLOOKUP(K445,'COD.'!$A$1:$B$39,2,0) -> Ocio y Entretenimiento
A446: 29/05/2025 | B446: 29/05/2025 | C446: =MONTH(A446) -> 5 | D446: Lidia sanchez | E446: Pago con tarjeta | F446: -80 | G446: EUR | H446: 6994.66 | I446: EUR | J446: 4940197133530195 LIDIA SANCHEZ BADALONA ES | K446: Peluqueria | L446: =VLOOKUP(K446,'COD.'!$A$1:$B$39,2,0) -> Ocio y Entretenimiento
A447: 29/05/2025 | B447: 29/05/2025 | C447: =MONTH(A447) -> 5 | D447: Bizum | E447: Enviado: yuleini | F447: -30 | G447: EUR | H447: 7074.66 | I447: EUR | J447: ENVIADO: Yuleini | K447: Limpieza casa | L447: =VLOOKUP(K447,'COD.'!$A$1:$B$39,2,0) -> Ocio y Entretenimiento
A448: 28/05/2025 | B448: 28/05/2025 | C448: =MONTH(A448) -> 5 | D448: J. sirvent | E448: Pago con tarjeta | F448: -4.55 | G448: EUR | H448: 7104.66 | I448: EUR | J448: 4940197133530195 J. SIRVENT SANTA COLOMA ES | K448: Bar/Restaurante | L448: =VLOOKUP(K448,'COD.'!$A$1:$B$39,2,0) -> Ocio y Entretenimiento
A449: 28/05/2025 | B449: 28/05/2025 | C449: =MONTH(A449) -> 5 | D449: Farmacia reixach - de pab | E449: Pago con tarjeta | F449: -74 | G449: EUR | H449: 7109.21 | I449: EUR | J449: 4940197133530195 FARMACIA REIXACH - DE PABBARCELONA ES | K449: Farmacia | L449: =VLOOKUP(K449,'COD.'!$A$1:$B$39,2,0) -> Salud y Cuidado
A450: 28/05/2025 | B450: 28/05/2025 | C450: =MONTH(A450) -> 5 | D450: Abono de nómina | E450: Transferencia nomina | F450: 1817.53 | G450: EUR | H450: 7183.21 | I450: EUR | J450: Transferencia nomina | K450: Nomina | L450: =VLOOKUP(K450,'COD.'!$A$1:$B$39,2,0) -> Transferencias y Efectivo
A451: 23/05/2025 | B451: 26/05/2025 | C451: =MONTH(A451) -> 5 | D451: Pp*p370b0e141 | E451: Pago con tarjeta | F451: -10.99 | G451: EUR | H451: 5365.68 | I451: EUR | J451: 4940197133530195 PP*P370B0E141 | K451: Spotify | L451: =VLOOKUP(K451,'COD.'!$A$1:$B$39,2,0) -> Ocio y Entretenimiento
A452: 24/05/2025 | B452: 26/05/2025 | C452: =MONTH(A452) -> 5 | D452: Don martin | E452: Pago con tarjeta | F452: -52.4 | G452: EUR | H452: 5376.67 | I452: EUR | J452: 4940197133530195 DON MARTIN SANTA COLOMA ES | K452: Bar/Restaurante | L452: =VLOOKUP(K452,'COD.'!$A$1:$B$39,2,0) -> Ocio y Entretenimiento
A453: 24/05/2025 | B453: 26/05/2025 | C453: =MONTH(A453) -> 5 | D453: Frankingfurt | E453: Pago con tarjeta | F453: -6.5 | G453: EUR | H453: 5429.07 | I453: EUR | J453: 4940197133530195 FRANKINGFURT STA. COLOMA DES | K453: Bar/Restaurante | L453: =VLOOKUP(K453,'COD.'!$A$1:$B$39,2,0) -> Ocio y Entretenimiento
... A510: 30/04/2025 | B510: 30/04/2025 | C510: =MONTH(A510) -> 4 | D510: Adeudo de aguas de barcelona | E510: Adeudo nº 2025120002944823 | F510: -43.58 | G510: EUR | H510: 5899.12 | I510: EUR | J510: N 2025120002944823 AIGUES DE BARCELONA | K510: Agua | L510: =VLOOKUP(K510,'COD.'!$A$1:$B$39,2,0) -> Suministros
A511: 30/04/2025 | B511: 30/04/2025 | C511: =MONTH(A511) -> 4 | D511: Cargo por amortizacion de prestamo/credito | F511: -431.25 | G511: EUR | H511: 5942.7 | I511: EUR | J511: 0182-3247-22-0830147409 | K511: Hipoteca | L511: =VLOOKUP(K511,'COD.'!$A$1:$B$39,2,0) -> Vivienda y Préstamos
A512: 29/04/2025 | B512: 29/04/2025 | C512: =MONTH(A512) -> 4 | D512: T1006 enrique tomas | E512: Pago con tarjeta | F512: -52.55 | G512: EUR | H512: 6373.95 | I512: EUR | J512: 4940197133530195 T1006 ENRIQUE TOMAS EL PRAT DE LLES | K512: Bar/Restaurante | L512: =VLOOKUP(K512,'COD.'!$A$1:$B$39,2,0) -> Ocio y Entretenimiento
A513: 29/04/2025 | B513: 29/04/2025 | C513: =MONTH(A513) -> 4 | D513: Adeudo de endesa | E513: Adeudo nº 2025119003019518 | F513: -73.96 | G513: EUR | H513: 6426.5 | I513: EUR | J513: N 2025119003019518 ENERGIA XXI CPVR | K513: Luz | L513: =VLOOKUP(K513,'COD.'!$A$1:$B$39,2,0) -> Suministros
A514: 29/04/2025 | B514: 29/04/2025 | C514: =MONTH(A514) -> 4 | D514: Abono de nómina | E514: Transferencia nomina | F514: 1867.53 | G514: EUR | H514: 6500.46 | I514: EUR | J514: Transferencia nomina | K514: Nomina | L514: =VLOOKUP(K514,'COD.'!$A$1:$B$39,2,0) -> Transferencias y Efectivo
A515: 28/04/2025 | B515: 28/04/2025 | C515: =MONTH(A515) -> 4 | D515: Consum b.gr.s.andreu | E515: Pago con tarjeta | F515: -30.98 | G515: EUR | H515: 4632.93 | I515: EUR | J515: 4940197133530195 CONSUM B.GR.S.ANDREU BARCELONA ES | K515: Supermercado | L515: =VLOOKUP(K515,'COD.'!$A$1:$B$39,2,0) -> Supermercado
A516: 27/04/2025 | B516: 28/04/2025 | C516: =MONTH(A516) -> 4 | D516: Ret. efectivo a debito con tarj. en cajero. aut. | E516: Otros | F516: -60 | G516: EUR | H516: 4663.91 | I516: EUR | J516: 4940197133530195 01821025 999 | K516: Limpieza casa | L516: =VLOOKUP(K516,'COD.'!$A$1:$B$39,2,0) -> Ocio y Entretenimiento
A517: 27/04/2025 | B517: 28/04/2025 | C517: =MONTH(A517) -> 4 | D517: Hyde park | E517: Pago con tarjeta | F517: -4.5 | G517: EUR | H517: 4723.91 | I517: EUR | J517: 4940197133530195 HYDE PARK BARCELONA ES | K517: Bar/Restaurante | L517: =VLOOKUP(K517,'COD.'!$A$1:$B$39,2,0) -> Ocio y Entretenimiento
A518: 27/04/2025 | B518: 28/04/2025 | C518: =MONTH(A518) -> 4 | D518: Bizum | E518: Enviado: regalo amaia | F518: -16.46 | G518: EUR | H518: 4728.41 | I518: EUR | J518: ENVIADO: Regalo Amaia | K518: Bizum | L518: =VLOOKUP(K518,'COD.'!$A$1:$B$39,2,0) -> Transferencias y Efectivo
A519: 27/04/2025 | B519: 28/04/2025 | C519: =MONTH(A519) -> 4 | D519: T mobilitat. app | E519: Pago con tarjeta | F519: -12.55 | G519: EUR | H519: 4744.87 | I519: EUR | J519: 4940197133530195 T MOBILITAT. APP HOSPITALET DEES | K519: Transporte | L519: =VLOOKUP(K519,'COD.'!$A$1:$B$39,2,0) -> Otros Gastos Generales
A520: 26/04/2025 | B520: 28/04/2025 | C520: =MONTH(A520) -> 4 | D520: Magic | E520: Pago con tarjeta | F520: -16 | G520: EUR | H520: 4757.42 | I520: EUR | J520: 4940197133530195 MAGIC BARCELONA ES | K520: Compras | L520: =VLOOKUP(K520,'COD.'!$A$1:$B$39,2,0) -> Ocio y Entretenimiento
A521: 26/04/2025 | B521: 28/04/2025 | C521: =MONTH(A521) -> 4 | D521: La bodegueta st andreu | E521: Pago con tarjeta | F521: -50.5 | G521: EUR | H521: 4773.42 | I521: EUR | J521: 4940197133530195 LA BODEGUETA ST ANDREU BARCELONA ES | K521: Bar/Restaurante | L521: =VLOOKUP(K521,'COD.'!$A$1:$B$39,2,0) -> Ocio y Entretenimiento
A522: 26/04/2025 | B522: 28/04/2025 | C522: =MONTH(A522) -> 4 | D522: Macxipa sant josep | E522: Pago con tarjeta | F522: -0.8 | G522: EUR | H522: 4823.92 | I522: EUR | J522: 4940197133530195 MACXIPA SANT JOSEP STA. COLOMA ES | K522: Bar/Restaurante | L522: =VLOOKUP(K522,'COD.'!$A$1:$B$39,2,0) -> Ocio y Entretenimiento
...

Sheet TD
A3: Suma de Importe | C3: Periodo
A4: Categoria | B4: Subcatergoria | C4: 1 | D4: 2 | E4: 3 | F4: 4 | G4: 5 | H4: 6 | I4: 7 | J4: 8 | K4: 9 | L4: 10 | M4: Total general
A5: BBVA | B5: Comision | C5: -35 | M5: -35
A6: Total BBVA | C6: -35 | M6: -35
A7: Moto | B7: Gasolina | C7: -11.32 | D7: -12.35 | F7: -12 | G7: -11 | H7: -11.86 | I7: -21.9 | K7: -79.37 | L7: -11 | M7: -170.8
B8: ITV | E8: -21.29 | M8: -21.29
B9: Parking | C9: -30 | D9: -30 | E9: -30 | F9: -30 | G9: -30 | H9: -30 | I9: -30 | J9: -30 | K9: -30 | L9: -30 | M9: -300
A10: Total Moto | C10: -41.32 | D10: -42.35 | E10: -51.29 | F10: -42 | G10: -41 | H10: -41.86 | I10: -51.9 | J10: -30 | K10: -109.37 | L10: -41 | M10: -492.09
A11: Ocio y Entretenimiento | B11: Apple cloud | C11: -2.99 | D11: -2.99 | E11: -2.99 | F11: -2.99 | G11: -2.99 | H11: -2.99 | I11: -2.99 | J11: -2.99 | K11: -5.48 | L11: -5.48 | M11: -34.88
B12: Bar/Restaurante | C12: -320.8 | D12: -18 | E12: -150.44 | F12: -286.98 | G12: -191.4 | H12: -228.15 | I12: -162.78 | J12: -439.01 | K12: -313.93 | L12: -174.61 | M12: -2286.1
B13: Compras | C13: -109.65 | D13: -130.86 | E13: -144.97 | F13: -157.68 | G13: -284 | H13: -172.32 | I13: -359.15 | J13: -468.61 | K13: -166.83 | L13: -167.65 | M13: -2161.72
B14: Gimnasio | D14: -65 | E14: -65 | F14: -65 | G14: -65 | H14: -65 | I14: -65 | J14: -32.5 | K14: -65 | L14: -65 | M14: -552.5
B15: Limpieza casa | E15: 72 | F15: -120 | G15: 42 | H15: -8 | I15: 72 | J15: 72 | K15: -90 | L15: 35.75 | M15: 75.75
B16: Loteria | C16: -10 | D16: -20 | E16: -10 | F16: -10 | G16: -10 | H16: -20 | L16: -10 | M16: -90
B17: Netfix | C17: -9.99 | D17: -9.99 | E17: -9.99 | F17: -9.99 | G17: -9.99 | H17: -6.99 | I17: -6.99 | J17: -6.99 | K17: -6.99 | L17: -6.99 | M17: -84.9
B18: Ocio | C18: -69 | F18: -56 | G18: -40 | H18: -103.3 | J18: -61.4 | L18: -3 | M18: -332.7
B19: Peluqueria | D19: -75 | F19: -90 | G19: -80 | M19: -245
B20: Podimo | H20: -0.99 | I20: -0.99 | J20: -0.99 | K20: -4.99 | L20: -4.99 | M20: -12.95
B21: Prime | I21: -49.9 | M21: -49.9
B22: Spotify | D22: -10.99 | E22: -10.99 | F22: -10.99 | G22: -10.99 | H22: -10.99 | I22: -10.99 | J22: -10.99 | K22: -11.99 | L22: -11.99 | M22: -100.91
B23: Uñas | F23: -42 | G23: -52 | H23: -49 | I23: -44 | M23: -187
B24: Viajes | F24: -641.4 | G24: -304 | I24: -208.63 | J24: -966.43 | K24: -165 | M24: -2285.46
A25: Total Ocio y Entretenimiento | C25: -522.43 | D25: -332.83 | E25: -322.38 | F25: -1493.03 | G25: -1008.37 | H25: -667.73 | I25: -839.42 | J25: -1917.91 | K25: -830.21 | L25: -413.96 | M25: -8348.27
A26: Otros Gastos Generales | B26: Donacion | C26: -9 | D26: -9 | E26: -9 | F26: -9 | G26: -9 | H26: -9 | I26: -9 | J26: -9 | K26: -9 | L26: -9 | M26: -90
B27: Tabaco | C27: -14.8 | D27: -15.4 | E27: -8.4 | F27: -18.2 | G27: -10.8 | H27: -23 | I27: -20.05 | J27: -16.5 | K27: -15.4 | L27: -34.7 | M27: -177.25
B28: Transporte | C28: -26.3 | E28: -26.26 | F28: -22.69 | G28: -8.66 | H28: -12.55 | J28: -17.97 | L28: -4.88 | M28: -119.31
A29: Total Otros Gastos Generales | C29: -50.1 | D29: -24.4 | E29: -43.66 | F29: -49.89 | G29: -28.46 | H29: -44.55 | I29: -29.05 | J29: -43.47 | K29: -24.4 | L29: -48.58 | M29: -386.56
A30: Salud y Cuidado | B30: Farmacia | C30: -121.03 | E30: -43.91 | F30: -57.9 | G30: -77.26 | H30: -329.11 | I30: -36.34 | J30: -81.86 | K30: -34.8 | L30: -222.79 | M30: -1005
A31: Total Salud y Cuidado | C31: -121.03 | E31: -43.91 | F31: -57.9 | G31: -77.26 | H31: -329.11 | I31: -36.34 | J31: -81.86 | K31: -34.8 | L31: -222.79 | M31: -1005
A32: Suministros | B32: Agua | D32: -44.2 | F32: -43.58 | H32: -44.47 | J32: -44.47 | L32: -44.47 | M32: -221.19
B33: Luz | C33: -125.9 | D33: -126.11 | E33: -214.2 | F33: -73.96 | H33: -103.37 | I33: -89.77 | K33: -88.34 | L33: -120.83 | M33: -942.48
B34: Vodafone | C34: -38.2 | D34: -38.2 | E34: -38.2 | F34: -38.2 | G34: -38.2 | H34: -38.2 | I34: -38.2 | J34: -38.2 | K34: -48.19 | L34: -42.2 | M34: -395.99
A35: Total Suministros | C35: -164.1 | D35: -208.51 | E35: -252.4 | F35: -155.74 | G35: -38.2 | H35: -186.04 | I35: -127.97 | J35: -82.67 | K35: -136.53 | L35: -207.5 | M35: -1559.66
A36: Supermercado | B36: Mascotas | C36: -52 | D36: -235.4 | E36: -80.67 | F36: -91.71 | G36: -155.14 | H36: -116.32 | I36: -122.05 | J36: -25.66 | K36: -157.1 | L36: -192 | M36: -1228.05
B37: Supermercado | C37: -197.18 | D37: -184.63 | E37: -120.26 | F37: -153.75 | G37: -143.9 | H37: -226.92 | I37: -157.6 | J37: -148.16 | K37: -188.37 | L37: -269.35 | M37: -1790.12
A38: Total Supermercado | C38: -249.18 | D38: -420.03 | E38: -200.93 | F38: -245.46 | G38: -299.04 | H38: -343.24 | I38: -279.65 | J38: -173.82 | K38: -345.47 | L38: -461.35 | M38: -3018.17
A39: Transferencias y Efectivo | B39: Bit2me | C39: 0 | M39: 0
B40: Bizum | C40: 122 | D40: 2 | E40: -381.67 | F40: 183.94 | G40: -58.75 | H40: -136 | I40: -75 | J40: 321 | K40: 100.09 | L40: -21 | M40: 56.61
B41: Efectivo | J41: 300 | M41: 300
B42: Nomina | C42: 1867.53 | D42: 1867.53 | E42: 1867.53 | F42: 1867.53 | G42: 1817.53 | H42: 1867.53 | I42: 1867.53 | J42: 1867.53 | K42: 1867.53 | L42: 1867.53 | M42: 18625.3
B43: Renta 2024 | G43: 973.39 | M43: 973.39
A44: Total Transferencias y Efectivo | C44: 1989.53 | D44: 1869.53 | E44: 1485.86 | F44: 2051.47 | G44: 2732.17 | H44: 1731.53 | I44: 1792.53 | J44: 2488.53 | K44: 1967.62 | L44: 1846.53 | M44: 19955.3
A45: Vivienda y Préstamos | B45: BBVA Seguro | C45: -55.54 | D45: -55.54 | E45: -55.51 | F45: -56.83 | G45: -56.83 | H45: -56.8 | I45: -56.56 | J45: -59.45 | K45: -59.45 | L45: -59.45 | M45: -571.96
B46: Casa | C46: -4.5 | D46: -13 | H46: -8.74 | I46: -3.48 | K46: -1 | L46: -47 | M46: -77.72
B47: Cuota mensual de fraccionamiento de gastos | C47: -83.93 | D47: -83.93 | E47: -83.93 | F47: -83.93 | G47: -83.97 | H47: 272.55 | I47: -92.48 | J47: 607.36 | K47: -92.49 | L47: -121.07 | M47: 154.18
B48: Fincas | C48: -50 | D48: -50 | E48: -50 | F48: -50 | G48: -50 | H48: -50 | I48: -50 | J48: -50 | K48: -50 | L48: -50 | M48: -500
B49: Hipoteca | C49: -431.01 | D49: -431.09 | E49: -431.17 | F49: -431.25 | G49: -431.33 | H49: -431.42 | I49: -461.91 | J49: -461.91 | K49: -461.91 | L49: -461.91 | M49: -4434.91
B50: Tributos | E50: -56.43 | H50: -56.43 | I50: -30.3 | K50: -56.43 | M50: -199.59
A51: Total Vivienda y Préstamos | C51: -624.98 | D51: -633.56 | E51: -677.04 | F51: -622.01 | G51: -622.13 | H51: -330.84 | I51: -694.73 | J51: 36 | K51: -721.28 | L51: -739.43 | M51: -5630
A52: Total general | C52: 181.39 | D52: 207.85 | E52: -105.75 | F52: -614.56 | G52: 617.71 | H52: -211.84 | I52: -266.53 | J52: 194.8 | K52: -234.44 | L52: -288.08 | M52: -519.45

Sheet COD.
A1: Subcatergoria | B1: Categoria
A2: Agua | B2: Suministros
A3: Apple cloud | B3: Ocio y Entretenimiento
A4: Bar/Restaurante | B4: Ocio y Entretenimiento
A5: BBVA Seguro | B5: Vivienda y Préstamos
A6: Bit2me | B6: Transferencias y Efectivo
A7: Bizum | B7: Transferencias y Efectivo
A8: Casa | B8: Vivienda y Préstamos
A9: Comision | B9: BBVA
A10: Compras | B10: Ocio y Entretenimiento
A11: Cuota mensual de fraccionamiento de gastos | B11: Vivienda y Préstamos
A12: Donacion | B12: Otros Gastos Generales
... A39: Vodafone | B39: Suministros
